{
  "skuContent": {
    "10046089": [
      {
        "additionalInfo": "<table><tbody><tr><th>Brand</th><td><p><a href='https://www.karlkustoms.com/brand/chevrolet-performance/' rel='tag'>Chevrolet Performance</a></p></td></tr></tbody></table>"
      }
    ],
    "10105117": [
      {
        "additionalInfo": "<table><tbody><tr><th>Brand</th><td><p><a href='https://www.karlkustoms.com/brand/chevrolet-performance/' rel='tag'>Chevrolet Performance</a></p></td></tr></tbody></table>"
      }
    ],
    "10185071": [
      {
        "additionalInfo": "<table><tbody><tr><th>Brand</th><td><p><a href='https://www.karlkustoms.com/brand/chevrolet-performance/' rel='tag'>Chevrolet Performance</a></p></td></tr></tbody></table>"
      }
    ],
    "12495490": [
      {
        "additionalInfo": "<table><tbody><tr><th>Brand</th><td><p><a href='https://www.karlkustoms.com/brand/chevrolet-performance/' rel='tag'>Chevrolet Performance</a></p></td></tr></tbody></table>"
      }
    ],
    "12551313": [
      {
        "additionalInfo": "<table><tbody><tr><th>Brand</th><td><p><a href='https://www.karlkustoms.com/brand/chevrolet-performance/' rel='tag'>Chevrolet Performance</a></p></td></tr></tbody></table>"
      }
    ],
    "12555331": [
      {
        "additionalInfo": "<table><tbody><tr><th>Brand</th><td><p><a href='https://www.karlkustoms.com/brand/chevrolet-performance/' rel='tag'>Chevrolet Performance</a></p></td></tr></tbody></table>"
      }
    ],
    "12562818": [
      {
        "additionalInfo": "<table><tbody><tr><th>Brand</th><td><p><a href='https://www.karlkustoms.com/brand/chevrolet-performance/' rel='tag'>Chevrolet Performance</a></p></td></tr></tbody></table>"
      }
    ],
    "12624262": [
      {
        "additionalInfo": "<table> <tbody><tr> <th>Weight</th> <td>377 lbs</td> </tr> <tr> <th>Dimensions</th> <td> 33 × 29.5 × 33 in</td> </tr> </tbody></table>"
      }
    ],
    "12670965": [
      {
        "additionalInfo": "<table><tbody><tr><th>Brand</th><td><p><a href='https://www.karlkustoms.com/brand/chevrolet-performance/' rel='tag'>Chevrolet Performance</a></p></td></tr></tbody></table>"
      }
    ],
    "12691674": [
      {
        "additionalInfo": "<table><tbody><tr><th>Weight</th><td>233 lbs</td></tr><tr><th>Brand</th><td><p><a href='https://www.karlkustoms.com/brand/chevrolet-performance/' rel='tag'>Chevrolet Performance</a></p></td></tr><tr><th>Replaces/Supersedes</th><td><p>19419042</p></td></tr></tbody></table>"
      }
    ],
    "12691728": [
      {
        "additionalInfo": "<table><tbody><tr><th>Brand</th><td><p><a href='https://www.karlkustoms.com/brand/chevrolet-performance/' rel='tag'>Chevrolet Performance</a></p></td></tr></tbody></table>"
      }
    ],
    "19154761": [
      {
        "additionalInfo": "<table><tbody><tr><th>Brand</th><td><p><a href='https://www.karlkustoms.com/brand/chevrolet-performance/' rel='tag'>Chevrolet Performance</a></p></td></tr></tbody></table>"
      }
    ],
    "19201171": [
      {
        "additionalInfo": "<table><tbody><tr><th>Brand</th><td><p><a href='https://www.karlkustoms.com/brand/chevrolet-performance/' rel='tag'>Chevrolet Performance</a></p></td></tr><tr><th>Replaces/Supersedes</th><td><p>88958693</p></td></tr></tbody></table>"
      }
    ],
    "19201172": [
      {
        "additionalInfo": "<table><tbody><tr><th>Brand</th><td><p><a href='https://www.karlkustoms.com/brand/chevrolet-performance/' rel='tag'>Chevrolet Performance</a></p></td></tr><tr><th>Replaces/Supersedes</th><td><p>88958694</p></td></tr></tbody></table>"
      }
    ],
    "19331572": [
      {
        "additionalInfo": "<table> <tbody><tr> <th>Weight</th> <td>520 lbs</td> </tr> <tr> <th>Brand</th> <td><p><a href='https://www.karlkustoms.com/brand/chevrolet-performance-powertrain/'>Chevrolet Performance Powertrain</a></p> </td> </tr>  </tbody></table>"
      }
    ],
    "19331581": [
      {
        "additionalInfo": "<table> <tbody> <tr> <th>Brand</th> <td><p><a href='https://www.karlkustoms.com/brand/chevrolet-performance-powertrain/'>Chevrolet Performance Powertrain</a></p> </td> </tr>  <tr> <th>Replaces/Supersedes</th> <td>12498792</td> </tr> </tbody></table>"
      }
    ],
    "19331583": [
      {
        "additionalInfo": "<table> <tbody><tr> <th>Weight</th> <td>680 lbs</td> </tr> <tr> <th>Brand</th> <td><p><a href='https://www.karlkustoms.com/brand/chevrolet-performance-powertrain/'>Chevrolet Performance Powertrain</a></p> </td> </tr>  <tr> <th>Replaces/Supersedes</th> <td>19201333</td> </tr> </tbody></table>"
      }
    ],
    "19331585": [
      {
        "additionalInfo": "<table> <tbody><tr> <th>Weight</th> <td>680 lbs</td> </tr> <tr> <th>Brand</th> <td><p><a href='https://www.karlkustoms.com/brand/chevrolet-performance-powertrain/'>Chevrolet Performance Powertrain</a></p> </td> </tr>  <tr> <th>Replaces/Supersedes</th> <td>19201334</td> </tr> </tbody></table>"
      }
    ],
    "19417356": [
      {
        "additionalInfo": "<table> <tbody><tr> <th>Weight</th> <td>539 lbs</td> </tr> <tr> <th>Brand</th> <td><p><a href='https://www.karlkustoms.com/brand/chevrolet-performance-powertrain/'>Chevrolet Performance Powertrain</a></p> </td> </tr> </tbody></table>"
      }
    ],
    "19417357": [
      {
        "additionalInfo": "<table> <tbody><tr> <th>Weight</th> <td>525 lbs</td> </tr> <tr> <th>Brand</th> <td><p><a href='https://www.karlkustoms.com/brand/chevrolet-performance-powertrain/'>Chevrolet Performance Powertrain</a></p> </td> </tr> <tr> <th>Replaces/Supersedes</th> <td>19260833, 19355573</td> </tr> </tbody></table>"
      }
    ],
    "19417592": [
      {
        "additionalInfo": "<table><tbody><tr><th>Brand</th><td><p><a href='https://www.karlkustoms.com/brand/chevrolet-performance/' rel='tag'>Chevrolet Performance</a></p></td></tr><tr><th>Replaces/Supersedes</th><td><p>12464298</p></td></tr></tbody></table>"
      }
    ],
    "19420455": [
      {
        "additionalInfo": "<table><tbody><tr><th>Brand</th><td><p><a href='https://www.karlkustoms.com/brand/chevrolet-performance/' rel='tag'>Chevrolet Performance</a></p></td></tr></tbody></table>"
      }
    ],
    "19421057": [
      {
        "additionalInfo": "<table> <tbody><tr> <th>Weight</th> <td>606 lbs</td> </tr> <tr> <th>Brand</th> <td><p><a href='https://www.karlkustoms.com/brand/chevrolet-performance-powertrain/'>Chevrolet Performance Powertrain</a></p> </td> </tr> <tr> <th>Replaces/Supersedes</th> <td>19370414</td> </tr> </tbody></table>"
      }
    ],
    "19421058": [
      {
        "additionalInfo": "<table> <tbody><tr> <th>Weight</th> <td>606 lbs</td> </tr> <tr> <th>Brand</th> <td><p><a href='https://www.karlkustoms.com/brand/chevrolet-performance-powertrain/'>Chevrolet Performance Powertrain</a></p> </td> </tr> <tr> <th>Replaces/Supersedes</th> <td>19370415</td> </tr> </tbody></table>"
      }
    ],
    "19431953": [
      {
        "additionalInfo": "<table> <tbody><tr> <th>Weight</th> <td>425 lbs</td> </tr> <tr> <th>Brand</th> <td><p><a href='https://www.karlkustoms.com/brand/chevrolet-performance-powertrain/'>Chevrolet Performance Powertrain</a></p> </td> </tr>  <tr> <th>Replaces/Supersedes</th> <td>19328728, 19355405, 19416592, 19418843</td> </tr> </tbody></table>"
      }
    ],
    "19431955": [
      {
        "additionalInfo": "<table> <tbody><tr> <th>Weight</th> <td>450 lbs</td> </tr> <tr> <th>Brand</th> <td><p><a href='https://www.karlkustoms.com/brand/chevrolet-performance-powertrain/'>Chevrolet Performance Powertrain</a></p> </td> </tr>  <tr> <th>Replaces/Supersedes</th> <td>19368622, 19417413, 19418844</td> </tr> </tbody></table>"
      }
    ],
    "19432060": [
      {
        "additionalInfo": "<table> <tbody><tr> <th>Weight</th> <td>680 lbs</td> </tr> <tr> <th>Brand</th> <td><p><a href='https://www.karlkustoms.com/brand/chevrolet-performance-powertrain/'>Chevrolet Performance Powertrain</a></p> </td> </tr>  </tbody></table>"
      }
    ],
    "19432298": [
      {
        "additionalInfo": "<table><tbody><tr><th>Brand</th><td><p><a href='https://www.karlkustoms.com/brand/chevrolet-performance/' rel='tag'>Chevrolet Performance</a></p></td></tr><tr><th>Replaces/Supersedes</th><td><p>12370838</p></td></tr></tbody></table>"
      }
    ],
    "19432776": [
      {
        "additionalInfo": "<table> <tbody><tr> <th>Weight</th> <td>531 lbs</td> </tr> <tr> <th>Brand</th> <td><p><a href='https://www.karlkustoms.com/brand/chevrolet-performance-powertrain/'>Chevrolet Performance Powertrain</a></p> </td> </tr> <tr> <th>Replaces/Supersedes</th> <td>19260831, 19332312</td> </tr> </tbody></table>"
      }
    ],
    "19432778": [
      {
        "additionalInfo": "<table><tbody><tr><th>Weight</th><td>473 lbs</td></tr><tr><th>Brand</th><td><p><a href='https://www.karlkustoms.com/brand/gm-oe-engine/' rel='tag'>GM OE Engine</a></p></td></tr><tr><th>Emissions</th><td><p>Please share VIN and current mileage in order notes for warranty documentation (if applicable)</p></td></tr><tr><th>Manufacturer Part Number</th><td><p>12703983</p></td></tr><tr><th>Replaces/Supersedes</th><td><p>12568758, 12681430, 12703983</p></td></tr></tbody></table>"
      }
    ],
    "19432779": [
      {
        "additionalInfo": "<table><tbody><tr><th>Weight</th><td>465 lbs</td></tr><tr><th>Brand</th><td><p><a href='https://www.karlkustoms.com/brand/gm-oe-engine/' rel='tag'>GM OE Engine</a></p></td></tr><tr><th>Emissions</th><td><p>Please share VIN and current mileage in order notes for warranty documentation (if applicable)</p></td></tr><tr><th>Manufacturer Part Number</th><td><p>12691672</p></td></tr></tbody></table>"
      }
    ],
    "19432780": [
      {
        "additionalInfo": "<table><tbody><tr><th>Weight</th><td>438 lbs</td></tr><tr><th>Brand</th><td><p><a href='https://www.karlkustoms.com/brand/gm-oe-engine/' rel='tag'>GM OE Engine</a></p></td></tr><tr><th>Emissions</th><td><p>Please share VIN and current mileage in order notes for warranty documentation (if applicable)</p></td></tr><tr><th>Manufacturer Part Number</th><td><p>12691673</p></td></tr></tbody></table>"
      }
    ],
    "19433030": [
      {
        "additionalInfo": "<table> <tbody><tr> <th>Weight</th> <td>298 lbs</td> </tr> <tr> <th>Brand</th> <td><p><a href='https://www.karlkustoms.com/brand/chevrolet-performance-powertrain/'>Chevrolet Performance Powertrain</a></p> </td> </tr>  <tr> <th>Replaces/Supersedes</th> <td>19210007, 19420878, 19431609</td> </tr> </tbody></table>"
      }
    ],
    "19433031": [
      {
        "additionalInfo": "<table> <tbody><tr> <th>Weight</th> <td>575 lbs</td> </tr> <tr> <th>Brand</th> <td><p><a href='https://www.karlkustoms.com/brand/chevrolet-performance-powertrain/'>Chevrolet Performance Powertrain</a></p> </td> </tr> <tr> <th>Manufacturer Part Number</th> <td>19419992</td> </tr> <tr> <th>Replaces/Supersedes</th> <td>19418192, 19419992, 19420880</td> </tr> </tbody></table>"
      }
    ],
    "19433032": [
      {
        "additionalInfo": "<table><tbody><tr><th>Weight</th><td>477 lbs</td></tr><tr><th>Brand</th><td><p><a href='https://www.karlkustoms.com/brand/chevrolet-performance/' rel='tag'>Chevrolet Performance</a></p></td></tr><tr><th>Replaces/Supersedes</th><td><p>12677167, 19367080, 19420870, 19431612</p></td></tr></tbody></table>"
      }
    ],
    "19433033": [
      {
        "additionalInfo": "<table> <tbody><tr> <th>Weight</th> <td>534 lbs</td> </tr> <tr> <th>Brand</th> <td><p><a href='https://www.karlkustoms.com/brand/chevrolet-performance-powertrain/'>Chevrolet Performance Powertrain</a></p> </td> </tr>  <tr> <th>Replaces/Supersedes</th> <td>12677170, 19367082, 19420871, 19420882, 19431613</td> </tr> </tbody></table>"
      }
    ],
    "19433034": [
      {
        "additionalInfo": "<table> <tbody><tr> <th>Weight</th> <td>652 lbs</td> </tr> <tr> <th>Brand</th> <td><p><a href='https://www.karlkustoms.com/brand/chevrolet-performance-powertrain/'>Chevrolet Performance Powertrain</a></p> </td> </tr>  <tr> <th>Replaces/Supersedes</th> <td>19367084, 19418190, 19420872, 19420883, 19431614</td> </tr> </tbody></table>"
      }
    ],
    "19433035": [
      {
        "additionalInfo": "<table> <tbody><tr> <th>Weight</th> <td>512 lbs</td> </tr> <tr> <th>Brand</th> <td><p><a href='https://www.karlkustoms.com/brand/chevrolet-performance-powertrain/'>Chevrolet Performance Powertrain</a></p> </td> </tr> <tr> <th>Replaces/Supersedes</th> <td>19355722, 19418657, 19432114</td> </tr> </tbody></table>"
      }
    ],
    "19433036": [
      {
        "additionalInfo": "<table> <tbody><tr> <th>Weight</th> <td>405 lbs</td> </tr> <tr> <th>Brand</th> <td><p><a href='https://www.karlkustoms.com/brand/chevrolet-performance-powertrain/'>Chevrolet Performance Powertrain</a></p> </td> </tr> <tr> <th>Replaces/Supersedes</th> <td>19355720, 19420884</td> </tr> </tbody></table>"
      }
    ],
    "19433037": [
      {
        "additionalInfo": "<table> <tbody><tr> <th>Weight</th> <td>335 lbs</td> </tr> <tr> <th>Brand</th> <td><p><a href='https://www.karlkustoms.com/brand/chevrolet-performance-powertrain/'>Chevrolet Performance Powertrain</a></p> </td> </tr>  <tr> <th>Replaces/Supersedes</th> <td>19417374, 19420877, 19420885</td> </tr> </tbody></table>"
      }
    ],
    "19433038": [
      {
        "additionalInfo": "<table> <tbody><tr> <th>Weight</th> <td>481 lbs</td> </tr> <tr> <th>Brand</th> <td><p><a href='https://www.karlkustoms.com/brand/chevrolet-performance-powertrain/'>Chevrolet Performance Powertrain</a></p> </td> </tr>  <tr> <th>Replaces/Supersedes</th> <td>19210008, 19420874, 19420879, 19431610</td> </tr> </tbody></table>"
      }
    ],
    "19433039": [
      {
        "additionalInfo": "<table> <tbody><tr> <th>Weight</th> <td>483 lbs</td> </tr> <tr> <th>Brand</th> <td><p><a href='https://www.karlkustoms.com/brand/chevrolet-performance-powertrain/'>Chevrolet Performance Powertrain</a></p> </td> </tr>  <tr> <th>Replaces/Supersedes</th> <td>19333157, 19417624, 19417781, 19432101</td> </tr> </tbody></table>"
      }
    ],
    "19433040": [
      {
        "additionalInfo": "<table> <tbody><tr> <th>Weight</th> <td>607 lbs</td> </tr> <tr> <th>Brand</th> <td><p><a href='https://www.karlkustoms.com/brand/chevrolet-performance-powertrain/'>Chevrolet Performance Powertrain</a></p> </td> </tr>  <tr> <th>Replaces/Supersedes</th> <td>19333158</td> </tr> </tbody></table>"
      }
    ],
    "19433041": [
      {
        "additionalInfo": "<table><tbody><tr><th>Weight</th><td>496 lbs</td></tr><tr><th>Brand</th><td><p><a href='https://www.karlkustoms.com/brand/chevrolet-performance/' rel='tag'>Chevrolet Performance</a></p></td></tr><tr><th>Replaces/Supersedes</th><td><p>19355668, 19417576, 19419205</p></td></tr></tbody></table>"
      }
    ],
    "19433043": [
      {
        "additionalInfo": "<table> <tbody><tr> <th>Weight</th> <td>510 lbs</td> </tr> <tr> <th>Brand</th> <td><p><a href='https://www.karlkustoms.com/brand/chevrolet-performance-powertrain/'>Chevrolet Performance Powertrain</a></p> </td> </tr>  <tr> <th>Replaces/Supersedes</th> <td>19368149</td> </tr> </tbody></table>"
      }
    ],
    "19433044": [
      {
        "additionalInfo": "<table> <tbody><tr> <th>Weight</th> <td>550 lbs</td> </tr> <tr> <th>Brand</th> <td><p><a href='https://www.karlkustoms.com/brand/chevrolet-performance-powertrain/'>Chevrolet Performance Powertrain</a></p> </td> </tr>  <tr> <th>Replaces/Supersedes</th> <td>19419000, 19432108</td> </tr> </tbody></table>"
      }
    ],
    "19433045": [
      {
        "additionalInfo": "<table> <tbody> <tr> <th>Brand</th> <td><p><a href='https://www.karlkustoms.com/brand/chevrolet-performance-powertrain/'>Chevrolet Performance Powertrain</a></p> </td> </tr> </tbody></table>"
      }
    ],
    "19433046": [
      {
        "additionalInfo": "<table> <tbody> <tr> <th>Brand</th> <td><p><a href='https://www.karlkustoms.com/brand/chevrolet-performance-powertrain/'>Chevrolet Performance Powertrain</a></p> </td> </tr> <tr> <th>Replaces/Supersedes</th> <td>19419199</td> </tr> </tbody></table>"
      }
    ],
    "19433047": [
      {
        "additionalInfo": "<table> <tbody><tr> <th>Weight</th> <td>346 lbs</td> </tr> <tr> <th>Brand</th> <td><p><a href='https://www.karlkustoms.com/brand/chevrolet-performance-powertrain/'>Chevrolet Performance Powertrain</a></p> </td> </tr> <tr> <th>Replaces/Supersedes</th> <td>19355719, 19418654</td> </tr> </tbody></table>"
      }
    ],
    "19433059": [
      {
        "additionalInfo": "<table> <tbody><tr> <th>Weight</th> <td>699 lbs</td> </tr> <tr> <th>Brand</th> <td><p><a href='https://www.karlkustoms.com/brand/chevrolet-performance-powertrain/'>Chevrolet Performance Powertrain</a></p> </td> </tr>  <tr> <th>Replaces/Supersedes</th> <td>19417593</td> </tr> </tbody></table>"
      }
    ],
    "19433063": [
      {
        "additionalInfo": "<table> <tbody><tr> <th>Weight</th> <td>600 lbs</td> </tr> <tr> <th>Brand</th> <td><p><a href='https://www.karlkustoms.com/brand/chevrolet-performance-powertrain/'>Chevrolet Performance Powertrain</a></p> </td> </tr> <tr> <th>Replaces/Supersedes</th> <td>12682080, 19418256</td> </tr> </tbody></table>"
      }
    ],
    "19433067": [
      {
        "additionalInfo": "<table> <tbody><tr> <th>Weight</th> <td>782 lbs</td> </tr> <tr> <th>Brand</th> <td><p><a href='https://www.karlkustoms.com/brand/chevrolet-performance-powertrain/'>Chevrolet Performance Powertrain</a></p> </td> </tr>  <tr> <th>Replaces/Supersedes</th> <td>19417727</td> </tr> </tbody></table>"
      }
    ],
    "19433071": [
      {
        "additionalInfo": "<table> <tbody><tr> <th>Weight</th> <td>782 lbs</td> </tr> <tr> <th>Brand</th> <td><p><a href='https://www.karlkustoms.com/brand/chevrolet-performance-powertrain/'>Chevrolet Performance Powertrain</a></p> </td> </tr>  <tr> <th>Replaces/Supersedes</th> <td>19356048</td> </tr> </tbody></table>"
      }
    ],
    "19433156": [
      {
        "additionalInfo": "<table> <tbody><tr> <th>Weight</th> <td>557 lbs</td> </tr> <tr> <th>Brand</th> <td><p><a href='https://www.karlkustoms.com/brand/chevrolet-performance-powertrain/'>Chevrolet Performance Powertrain</a></p> </td> </tr>  <tr> <th>Replaces/Supersedes</th> <td>88890534</td> </tr> </tbody></table>"
      }
    ],
    "19433157": [
      {
        "additionalInfo": "<table> <tbody><tr> <th>Weight</th> <td>602 lbs</td> </tr> <tr> <th>Brand</th> <td><p><a href='https://www.karlkustoms.com/brand/chevrolet-performance-powertrain/'>Chevrolet Performance Powertrain</a></p> </td> </tr>  <tr> <th>Replaces/Supersedes</th> <td>24502620</td> </tr> </tbody></table>"
      }
    ],
    "19433158": [
      {
        "additionalInfo": "<table> <tbody><tr> <th>Weight</th> <td>402 lbs</td> </tr> <tr> <th>Brand</th> <td><p><a href='https://www.karlkustoms.com/brand/chevrolet-performance-powertrain/'>Chevrolet Performance Powertrain</a></p> </td> </tr>  <tr> <th>Replaces/Supersedes</th> <td>24502619</td> </tr> </tbody></table>"
      }
    ],
    "19433160": [
      {
        "additionalInfo": "<table> <tbody><tr> <th>Weight</th> <td>532 lbs</td> </tr> <tr> <th>Brand</th> <td><p><a href='https://www.karlkustoms.com/brand/chevrolet-performance-powertrain/'>Chevrolet Performance Powertrain</a></p> </td> </tr>  <tr> <th>Replaces/Supersedes</th> <td>19331576, 19419002</td> </tr> </tbody></table>"
      }
    ],
    "19433162": [
      {
        "additionalInfo": "<table> <tbody><tr> <th>Weight</th> <td>611 lbs</td> </tr> <tr> <th>Brand</th> <td><p><a href='https://www.karlkustoms.com/brand/chevrolet-performance-powertrain/'>Chevrolet Performance Powertrain</a></p> </td> </tr>  <tr> <th>Replaces/Supersedes</th> <td>19201332, 19331579</td> </tr> </tbody></table>"
      }
    ],
    "19433375": [
      {
        "additionalInfo": "<table> <tbody><tr> <th>Weight</th> <td>361 lbs</td> </tr> <tr> <th>Brand</th> <td><p><a href='https://www.karlkustoms.com/brand/chevrolet-performance-powertrain/'>Chevrolet Performance Powertrain</a></p> </td> </tr>  <tr> <th>Replaces/Supersedes</th> <td>12498778</td> </tr> </tbody></table>"
      }
    ],
    "19433409": [
      {
        "additionalInfo": "<table> <tbody><tr> <th>Weight</th> <td>590 lbs</td> </tr> <tr> <th>Brand</th> <td><p><a href='https://www.karlkustoms.com/brand/chevrolet-performance-powertrain/'>Chevrolet Performance Powertrain</a></p> </td> </tr>  <tr> <th>Replaces/Supersedes</th> <td>12568774</td> </tr> </tbody></table>"
      }
    ],
    "19433410": [
      {
        "additionalInfo": "<table> <tbody><tr> <th>Weight</th> <td>522 lbs</td> </tr> <tr> <th>Brand</th> <td><p><a href='https://www.karlkustoms.com/brand/chevrolet-performance-powertrain/'>Chevrolet Performance Powertrain</a></p> </td> </tr>  <tr> <th>Replaces/Supersedes</th> <td>12498777, 19419001</td> </tr> </tbody></table>"
      }
    ],
    "19433748": [
      {
        "additionalInfo": "<table> <tbody><tr> <th>Weight</th> <td>425 lbs</td> </tr> <tr> <th>Brand</th> <td><p><a href='https://www.karlkustoms.com/brand/chevrolet-performance-powertrain/'>Chevrolet Performance Powertrain</a></p> </td> </tr>  </tbody></table>"
      }
    ],
    "19433750": [
      {
        "additionalInfo": "<table> <tbody><tr> <th>Weight</th> <td>425 lbs</td> </tr> <tr> <th>Brand</th> <td><p><a href='https://www.karlkustoms.com/brand/chevrolet-performance-powertrain/'>Chevrolet Performance Powertrain</a></p> </td> </tr> </tbody></table>"
      }
    ],
    "19434034": [
      {
        "additionalInfo": "<table><tbody><tr><th>Brand</th><td><p><a href='https://www.karlkustoms.com/brand/chevrolet-performance/' rel='tag'>Chevrolet Performance</a></p></td></tr></tbody></table>"
      }
    ],
    "19434598": [
      {
        "additionalInfo": "<table> <tbody><tr> <th>Weight</th> <td>427 lbs</td> </tr> <tr> <th>Brand</th> <td><p><a href='https://www.karlkustoms.com/brand/chevrolet-performance-powertrain/'>Chevrolet Performance Powertrain</a></p> </td> </tr>  <tr> <th>Replaces/Supersedes</th> <td>19331563, 19421061</td> </tr> </tbody></table>"
      }
    ],
    "19434602": [
      {
        "additionalInfo": "<table> <tbody> <tr> <th>Replaces/Supersedes</th> <td>19258602, 19318602, 19370602, 19418602, 19431602, 19432602, 88869602</td> </tr> </tbody></table>"
      }
    ],
    "19434604": [
      {
        "additionalInfo": "<table> <tbody> <tr> <th>Brand</th> <td><p><a href='https://www.karlkustoms.com/brand/chevrolet-performance-powertrain/'>Chevrolet Performance Powertrain</a></p> </td> </tr>  <tr> <th>Replaces/Supersedes</th> <td>19419604, 19433604, 88869604</td> </tr> </tbody></table>"
      }
    ],
    "19434640": [
      {
        "additionalInfo": "<table><tbody><tr><th>Weight</th><td>415 lbs</td></tr><tr><th>Brand</th><td><p><a href='https://www.karlkustoms.com/brand/chevrolet-performance-powertrain/' rel='tag'>Chevrolet Performance Powertrain</a></p></td></tr><tr><th>Replaces/Supersedes</th><td><p>19370412, 194342420</p></td></tr></tbody></table>"
      }
    ],
    "19434650": [
      {
        "additionalInfo": "<table> <tbody><tr> <th>Weight</th> <td>486 lbs</td> </tr> <tr> <th>Brand</th> <td><p><a href='https://www.karlkustoms.com/brand/chevrolet-performance-powertrain/'>Chevrolet Performance Powertrain</a></p> </td> </tr> <tr> <th>Manufacturer Part Number</th> <td>19434650</td> </tr> <tr> <th>Replaces/Supersedes</th> <td>19432690</td> </tr> </tbody></table>"
      }
    ],
    "19435005": [
      {
        "additionalInfo": "<table><tbody><tr><th>Weight</th><td>400 lbs</td></tr></tbody></table>"
      }
    ],
    "19435098": [
      {
        "additionalInfo": "<table> <tbody><tr> <th>Weight</th> <td>415 lbs</td> </tr> <tr> <th>Brand</th> <td><p><a href='https://www.karlkustoms.com/brand/chevrolet-performance-powertrain/'>Chevrolet Performance Powertrain</a></p> </td> </tr> <tr> <th>Replaces/Supersedes</th> <td>19301326, 19370416, 19432414 </td> </tr> </tbody></table>"
      }
    ],
    "19435100": [
      {
        "additionalInfo": "<table> <tbody><tr> <th>Weight</th> <td>415 lbs</td> </tr> <tr> <th>Brand</th> <td><p><a href='https://www.karlkustoms.com/brand/chevrolet-performance-powertrain/'>Chevrolet Performance Powertrain</a></p> </td> </tr> <tr> <th>Replaces/Supersedes</th> <td>19419864, 19432416, 19434638</td> </tr> </tbody></table>"
      }
    ],
    "19435104": [
      {
        "additionalInfo": "<table> <tbody><tr> <th>Weight</th> <td>415 lbs</td> </tr> <tr> <th>Brand</th> <td><p><a href='https://www.karlkustoms.com/brand/chevrolet-performance-powertrain/'>Chevrolet Performance Powertrain</a></p> </td> </tr> <tr> <th>Replaces/Supersedes</th> <td>19301360, 19369338, 19370413, 19419866, 19432418</td> </tr> </tbody></table>"
      }
    ],
    "19435106": [
      {
        "additionalInfo": "<table> <tbody><tr> <th>Weight</th> <td>486 lbs</td> </tr> <tr> <th>Brand</th> <td><p><a href='https://www.karlkustoms.com/brand/chevrolet-performance-powertrain/'>Chevrolet Performance Powertrain</a></p> </td> </tr> <tr> <th>Manufacturer Part Number</th> <td>19432422</td> </tr> <tr> <th>Replaces/Supersedes</th> <td>19420382, 19432422, 19434644</td> </tr> </tbody></table>"
      }
    ],
    "19435115": [
      {
        "additionalInfo": "<table><tbody><tr><th>Brand</th><td><p><a href='https://www.karlkustoms.com/brand/chevrolet-performance/' rel='tag'>Chevrolet Performance</a></p></td></tr></tbody></table>"
      }
    ],
    "24502476": [
      {
        "additionalInfo": "<table><tbody><tr><th>Weight</th><td>9.56 lbs</td></tr><tr><th>Brand</th><td><p><a href='https://www.karlkustoms.com/brand/chevrolet-performance/' rel='tag'>Chevrolet Performance</a></p></td></tr></tbody></table>"
      }
    ],
    "CPSLS36LMAN": [
      {
        "additionalInfo": "<table> <tbody> <tr> <th>Brand</th> <td><p><a href='https://www.karlkustoms.com/brand/chevrolet-performance-powertrain/' rel='tag'>Chevrolet Performance Powertrain</a></p></td> </tr> </tbody></table>"
      }
    ],
    "CPSLS34306L80E2400": [
      {
        "additionalInfo": "<table> <tbody> <tr> <th>Brand</th> <td><p><a href='https://www.karlkustoms.com/brand/chevrolet-performance-powertrain/' rel='tag'>Chevrolet Performance Powertrain</a></p></td> </tr> </tbody></table>"
      }
    ],
    "CPSLS3EROD6L80E": [
      {
        "additionalInfo": "<table> <tbody> <tr> <th>Brand</th> <td><p><a href='https://www.karlkustoms.com/brand/chevrolet-performance-powertrain/' rel='tag'>Chevrolet Performance Powertrain</a></p></td> </tr> </tbody></table>"
      }
    ],
    "CPSLS35254L75E": [
      {
        "additionalInfo": "<table> <tbody> <tr> <th>Brand</th> <td><p><a href='https://www.karlkustoms.com/brand/chevrolet-performance-powertrain/' rel='tag'>Chevrolet Performance Powertrain</a></p></td> </tr> </tbody></table>"
      }
    ],
    "CPSLT18L90EW": [
      {
        "additionalInfo": "<table> <tbody> <tr> <th>Brand</th> <td><p><a href='https://www.karlkustoms.com/brand/chevrolet-performance-powertrain/' rel='tag'>Chevrolet Performance Powertrain</a></p></td> </tr> </tbody></table>"
      }
    ],
    "CPSSP383EFIT56": [
      {
        "additionalInfo": "<table> <tbody> <tr> <th>Brand</th> <td><p><a href='https://www.karlkustoms.com/brand/chevrolet-performance-powertrain/' rel='tag'>Chevrolet Performance Powertrain</a></p></td> </tr> </tbody></table>"
      }
    ],
    "CPSLS3765156LMAN": [
      {
        "additionalInfo": "<table> <tbody> <tr> <th>Brand</th> <td><p><a href='https://www.karlkustoms.com/brand/chevrolet-performance-powertrain/' rel='tag'>Chevrolet Performance Powertrain</a></p></td> </tr> </tbody></table>"
      }
    ],
    "CPSSP383EFI4L70E": [
      {
        "additionalInfo": "<table> <tbody> <tr> <th>Brand</th> <td><p><a href='https://www.karlkustoms.com/brand/chevrolet-performance-powertrain/' rel='tag'>Chevrolet Performance Powertrain</a></p></td> </tr> </tbody></table>"
      }
    ],
    "CPSLT1WET6LMAN": [
      {
        "additionalInfo": "<table> <tbody> <tr> <th>Brand</th> <td><p><a href='https://www.karlkustoms.com/brand/chevrolet-performance-powertrain/' rel='tag'>Chevrolet Performance Powertrain</a></p></td> </tr> </tbody></table>"
      }
    ],
    "CPSLT14L70EW": [
      {
        "additionalInfo": "<table> <tbody> <tr> <th>Brand</th> <td><p><a href='https://www.karlkustoms.com/brand/chevrolet-performance-powertrain/' rel='tag'>Chevrolet Performance Powertrain</a></p></td> </tr> </tbody></table>"
      }
    ],
    "CPSLS35256L80E3000": [
      {
        "additionalInfo": "<table> <tbody> <tr> <th>Brand</th> <td><p><a href='https://www.karlkustoms.com/brand/chevrolet-performance-powertrain/' rel='tag'>Chevrolet Performance Powertrain</a></p></td> </tr> </tbody></table>"
      }
    ],
    "CPSLS3765256LMAN": [
      {
        "additionalInfo": "<table> <tbody> <tr> <th>Brand</th> <td><p><a href='https://www.karlkustoms.com/brand/chevrolet-performance-powertrain/' rel='tag'>Chevrolet Performance Powertrain</a></p></td> </tr> </tbody></table>"
      }
    ],
    "CPSLS3764806LMAN": [
      {
        "additionalInfo": "<table> <tbody> <tr> <th>Brand</th> <td><p><a href='https://www.karlkustoms.com/brand/chevrolet-performance-powertrain/' rel='tag'>Chevrolet Performance Powertrain</a></p></td> </tr> </tbody></table>"
      }
    ],
    "CPSLS36LMANEROD": [
      {
        "additionalInfo": "<table> <tbody> <tr> <th>Brand</th> <td><p><a href='https://www.karlkustoms.com/brand/chevrolet-performance-powertrain/' rel='tag'>Chevrolet Performance Powertrain</a></p></td> </tr> </tbody></table>"
      }
    ],
    "CPSLS34L70E": [
      {
        "additionalInfo": "<table> <tbody> <tr> <th>Brand</th> <td><p><a href='https://www.karlkustoms.com/brand/chevrolet-performance-powertrain/' rel='tag'>Chevrolet Performance Powertrain</a></p></td> </tr> </tbody></table>"
      }
    ],
    "CPSLT4W10L90E": [
      {
        "additionalInfo": "<table> <tbody><tr> <th>Brand</th> <td><p><a href='https://www.karlkustoms.com/brand/chevrolet-performance-powertrain/' rel='tag'>Chevrolet Performance Powertrain</a></p> </td> </tr> </tbody></table>"
      }
    ],
    "CPSLT4W8L90E": [
      {
        "additionalInfo": "<table> <tbody><tr> <th>Brand</th> <td><p><a href='https://www.karlkustoms.com/brand/chevrolet-performance-powertrain/' rel='tag'>Chevrolet Performance Powertrain</a></p> </td> </tr> </tbody></table>"
      }
    ],
    "CPSZZ5726204L85E": [
      {
        "additionalInfo": "<table> <tbody><tr> <th>Brand</th> <td><p><a href='https://www.karlkustoms.com/brand/chevrolet-performance-powertrain/' rel='tag'>Chevrolet Performance Powertrain</a></p> </td> </tr> </tbody></table>"
      }
    ],
    "CPSLT4W4L75E": [
      {
        "additionalInfo": "<table> <tbody><tr> <th>Brand</th> <td><p><a href='https://www.karlkustoms.com/brand/chevrolet-performance-powertrain/' rel='tag'>Chevrolet Performance Powertrain</a></p> </td> </tr> </tbody></table>"
      }
    ],
    "CPSLT4ERODW8L90E": [
      {
        "additionalInfo": "<table> <tbody><tr> <th>Brand</th> <td><p><a href='https://www.karlkustoms.com/brand/chevrolet-performance-powertrain/' rel='tag'>Chevrolet Performance Powertrain</a></p> </td> </tr> </tbody></table>"
      }
    ],
    "CPSSP383EFITK4L70E": [
      {
        "additionalInfo": "<table> <tbody><tr> <th>Brand</th> <td><p><a href='https://www.karlkustoms.com/brand/chevrolet-performance-powertrain/' rel='tag'>Chevrolet Performance Powertrain</a></p> </td> </tr> </tbody></table>"
      }
    ],
    "CPSSP383EFITKT56": [
      {
        "additionalInfo": "<table> <tbody><tr> <th>Brand</th> <td><p><a href='https://www.karlkustoms.com/brand/chevrolet-performance-powertrain/' rel='tag'>Chevrolet Performance Powertrain</a></p> </td> </tr> </tbody></table>"
      }
    ],
    "CPSZZ4274806LMAN": [
      {
        "additionalInfo": "<table> <tbody><tr> <th>Brand</th> <td><p><a href='https://www.karlkustoms.com/brand/chevrolet-performance-powertrain/' rel='tag'>Chevrolet Performance Powertrain</a></p> </td> </tr> </tbody></table>"
      }
    ],
    "CPSZZ6EFITK4L65E": [
      {
        "additionalInfo": "<table> <tbody><tr> <th>Brand</th> <td><p><a href='https://www.karlkustoms.com/brand/chevrolet-performance-powertrain/' rel='tag'>Chevrolet Performance Powertrain</a></p> </td> </tr> </tbody></table>"
      }
    ],
    "CPSZZ6EFITKT56": [
      {
        "additionalInfo": "<table> <tbody><tr> <th>Brand</th> <td><p><a href='https://www.karlkustoms.com/brand/chevrolet-performance-powertrain/' rel='tag'>Chevrolet Performance Powertrain</a></p> </td> </tr> </tbody></table>"
      }
    ],
    "CPSZZ5726206LMAN": [
      {
        "additionalInfo": "<table> <tbody><tr> <th>Brand</th> <td><p><a href='https://www.karlkustoms.com/brand/chevrolet-performance-powertrain/' rel='tag'>Chevrolet Performance Powertrain</a></p> </td> </tr> </tbody></table>"
      }
    ],
    "CPSZZ6TK4L65E": [
      {
        "additionalInfo": "<table> <tbody><tr> <th>Brand</th> <td><p><a href='https://www.karlkustoms.com/brand/chevrolet-performance-powertrain/' rel='tag'>Chevrolet Performance Powertrain</a></p> </td> </tr> </tbody></table>"
      }
    ],
    "CPSSP350385TK4L65E": [
      {
        "additionalInfo": "<table> <tbody><tr> <th>Brand</th> <td><p><a href='https://www.karlkustoms.com/brand/chevrolet-performance-powertrain/' rel='tag'>Chevrolet Performance Powertrain</a></p> </td> </tr> </tbody></table>"
      }
    ],
    "CPSSP350385TKT56": [
      {
        "additionalInfo": "<table> <tbody><tr> <th>Brand</th> <td><p><a href='https://www.karlkustoms.com/brand/chevrolet-performance-powertrain/' rel='tag'>Chevrolet Performance Powertrain</a></p> </td> </tr> </tbody></table>"
      }
    ],
    "CPSZZ6EFI4L65E": [
      {
        "additionalInfo": "<table> <tbody><tr> <th>Brand</th> <td><p><a href='https://www.karlkustoms.com/brand/chevrolet-performance-powertrain/' rel='tag'>Chevrolet Performance Powertrain</a></p> </td> </tr> </tbody></table>"
      }
    ],
    "CPSZZ6EFIT56": [
      {
        "additionalInfo": "<table> <tbody><tr> <th>Brand</th> <td><p><a href='https://www.karlkustoms.com/brand/chevrolet-performance-powertrain/' rel='tag'>Chevrolet Performance Powertrain</a></p> </td> </tr> </tbody></table>"
      }
    ],
    "CPSSP3836LMAN": [
      {
        "additionalInfo": "<table> <tbody><tr> <th>Brand</th> <td><p><a href='https://www.karlkustoms.com/brand/chevrolet-performance-powertrain/' rel='tag'>Chevrolet Performance Powertrain</a></p></td></tr></tbody></table>"
      }
    ],
    "CPSSP350357TKT56": [
      {
        "additionalInfo": "<table><tbody><tr><th>Brand</th><td><p><a href='https://www.karlkustoms.com/brand/chevrolet-performance-powertrain/' rel='tag'>Chevrolet Performance Powertrain</a></p></td></tr></tbody></table>"
      }
    ],
    "CPSLT4W6L80E": [
      {
        "additionalInfo": "<table><tbody><tr><th>Brand</th><td><p><a href='https://www.karlkustoms.com/brand/chevrolet-performance-powertrain/' rel='tag'>Chevrolet Performance Powertrain</a></p></td></tr></tbody></table>"
      }
    ],
    "CPSZZ5025026LMAN": [
      {
        "additionalInfo": "<table><tbody><tr><th>Brand</th><td><p><a href='https://www.karlkustoms.com/brand/chevrolet-performance-powertrain/' rel='tag'>Chevrolet Performance Powertrain</a></p></td></tr></tbody></table>"
      }
    ],
    "19434604d2": [
      {
        "additionalInfo": "<table><tbody><tr><th>Brand</th><td><p><a href='https://www.karlkustoms.com/brand/chevrolet-performance-powertrain/' rel='tag'>Chevrolet Performance Powertrain</a></p></td></tr><tr><th>Manufacturer Part Number</th><td><p>PK604D2</p></td></tr><tr><th>Replaces/Supersedes</th><td><p>19419604D2, 19433604D2</p></td></tr></tbody></table>"
      }
    ],
    "CPSZZ4274L70E": [
      {
        "additionalInfo": "<table><tbody><tr><th>Brand</th><td><p><a href='https://www.karlkustoms.com/brand/chevrolet-performance-powertrain/' rel='tag'>Chevrolet Performance Powertrain</a></p></td></tr></tbody></table>"
      }
    ],
    "CPSZZ5024L85E": [
      {
        "additionalInfo": "<table><tbody><tr><th>Brand</th><td><p><a href='https://www.karlkustoms.com/brand/chevrolet-performance-powertrain/' rel='tag'>Chevrolet Performance Powertrain</a></p></td></tr></tbody></table>"
      }
    ],
    "CPSLS3765254L70E": [
      {
        "additionalInfo": "<table><tbody><tr><th>Brand</th><td><p><a href='https://www.karlkustoms.com/brand/chevrolet-performance-powertrain/' rel='tag'>Chevrolet Performance Powertrain</a></p></td></tr></tbody></table>"
      }
    ],
    "CPSLS3764804L70E": [
      {
        "additionalInfo": "<table><tbody><tr><th>Brand</th><td><p><a href='https://www.karlkustoms.com/brand/chevrolet-performance-powertrain/' rel='tag'>Chevrolet Performance Powertrain</a></p></td></tr></tbody></table>"
      }
    ],
    "CPSLS34X4L70E": [
      {
        "additionalInfo": "<table><tbody><tr><th>Brand</th><td><p><a href='https://www.karlkustoms.com/brand/chevrolet-performance-powertrain/' rel='tag'>Chevrolet Performance Powertrain</a></p></td></tr></tbody></table>"
      }
    ],
    "CPSLS34L65E": [
      {
        "additionalInfo": "<table><tbody><tr><th>Brand</th><td><p><a href='https://www.karlkustoms.com/brand/chevrolet-performance-powertrain/' rel='tag'>Chevrolet Performance Powertrain</a></p></td></tr></tbody></table>"
      }
    ],
    "CPSLS3EROD4L65E": [
      {
        "additionalInfo": "<table><tbody><tr><th>Brand</th><td><p><a href='https://www.karlkustoms.com/brand/chevrolet-performance-powertrain/' rel='tag'>Chevrolet Performance Powertrain</a></p></td></tr></tbody></table>"
      }
    ],
    "CPSSP3834L70E": [
      {
        "additionalInfo": "<table><tbody><tr><th>Brand</th><td><p><a href='https://www.karlkustoms.com/brand/chevrolet-performance-powertrain/' rel='tag'>Chevrolet Performance Powertrain</a></p></td></tr></tbody></table>"
      }
    ],
    "CPSZZ6TKT56": [
      {
        "additionalInfo": "<table><tbody><tr><th>Brand</th><td><p><a href='https://www.karlkustoms.com/brand/chevrolet-performance-powertrain/' rel='tag'>Chevrolet Performance Powertrain</a></p></td></tr></tbody></table>"
      }
    ],
    "CPSLS34806L80E3000": [
      {
        "additionalInfo": "<table><tbody><tr><th>Brand</th><td><p><a href='https://www.karlkustoms.com/brand/chevrolet-performance-powertrain/' rel='tag'>Chevrolet Performance Powertrain</a></p></td></tr></tbody></table>"
      }
    ],
    "CPSLS3765154L70E": [
      {
        "additionalInfo": "<table><tbody><tr><th>Brand</th><td><p><a href='https://www.karlkustoms.com/brand/chevrolet-performance-powertrain/' rel='tag'>Chevrolet Performance Powertrain</a></p></td></tr></tbody></table>"
      }
    ],
    "CPS350HOTK4L65E": [
      {
        "additionalInfo": "<table><tbody><tr><th>Brand</th><td><p><a href='https://www.karlkustoms.com/brand/chevrolet-performance-powertrain/' rel='tag'>Chevrolet Performance Powertrain</a></p></td></tr></tbody></table>"
      }
    ],
    "KPMUSMTSSPEC": [
      {
        "additionalInfo": "<table><tbody><tr><th>Brand</th><td><p><a href='https://www.karlkustoms.com/brand/karl-performance-engines-1/' rel='tag'>Karl Performance Engines</a></p></td></tr></tbody></table>"
      }
    ],
    "KPMIMCASCSPEC": [
      {
        "additionalInfo": "<table><tbody><tr><th>Brand</th><td><p><a href='https://www.karlkustoms.com/brand/karl-performance-engines-1/' rel='tag'>Karl Performance Engines</a></p></td></tr></tbody></table>"
      }
    ],
    "KPMCC355F4": [
      {
        "additionalInfo": "<table><tbody><tr><th>Brand</th><td><p><a href='https://www.karlkustoms.com/brand/karl-performance-engines-1/' rel='tag'>Karl Performance Engines</a></p></td></tr></tbody></table>"
      }
    ]
  }
}